cadwyn/__init__.py
cadwyn/__main__.py
cadwyn/_asts.py
cadwyn/_importer.py
cadwyn/_render.py
cadwyn/_utils.py
cadwyn/applications.py
cadwyn/changelogs.py
cadwyn/dependencies.py
cadwyn/exceptions.py
cadwyn/middleware.py
cadwyn/py.typed
cadwyn/route_generation.py
cadwyn/routing.py
cadwyn/schema_generation.py
cadwyn/_internal/__init__.py
cadwyn/_internal/context_vars.py
cadwyn/static/__init__.py
cadwyn/static/docs.html
cadwyn/structure/__init__.py
cadwyn/structure/common.py
cadwyn/structure/data.py
cadwyn/structure/endpoints.py
cadwyn/structure/enums.py
cadwyn/structure/schemas.py
cadwyn/structure/versions.py
cadwyn-6.0.1.dist-info/METADATA
cadwyn-6.0.1.dist-info/WHEEL
cadwyn-6.0.1.dist-info/entry_points.txt
cadwyn-6.0.1.dist-info/licenses/LICENSE
cadwyn-6.0.1.dist-info/RECORD
